{
    "path" : "./",
    "import" : {
        "box" : "ModelJsons/box.json",
        "camera" : "ModelJsons/cameraModel.json",
        "plane" : "ModelJsons/plane.json"
    },
    "nodes" : [
        {
            "name" : "box",
            "pos" : [0,-0.5,0]
        },
        {
            "name" : "box",
            "pos" : [1.4,-0.5,1],
            "rotation" : [0,45,0]
        },
        {
            "name" : "box",
            "pos" : [-2,-0.5,2],
            "rotation" : [0,45,0]
        },
        {
            "name" : "camera",
            "pos" : [-3,-0,-3],
            "rotation" : [0,40,0]
        },
        {
            "name" : "camera",
            "pos" : [2,0,-3],
            "rotation" : [0,-40,0]
        },
        {
            "name" : "plane",
            "pos" : [-0.5,0,-3],
            "rotation" : [90,0,90],
            "scale" : [1,4,4]
        }
    ],
    "cameras":[
        {
            "pos": [-8,5,-1.5],
            "filename" : "test.png",
            "f" : 0.8,
            "eular" : [0,107,35],
            "w" : 1,
            "h" : 1,
            "dx" : 0.5,
            "dy" : 0.5,
            "width" : 2048,
            "height" : 2048
        },
        {
            "pos": [-0.5,5,1],
            "filename" : "test2.png",
            "f" : 0.5,
            "eular" : [90,0,0],
            "w" : 1,
            "h" : 1,
            "dx" : 0.5,
            "dy" : 0.5,
            "width" : 2048,
            "height" : 2048
        }
    ]
}